README.md
setup.py
mssapi/__init__.py
mssapi/auth.py
mssapi/auth_handler.py
mssapi/compat.py
mssapi/connection.py
mssapi/exception.py
mssapi/handler.py
mssapi/https_connection.py
mssapi/jsonresponse.py
mssapi/plugin.py
mssapi/provider.py
mssapi/regioninfo.py
mssapi/requestlog.py
mssapi/resultset.py
mssapi/storage_uri.py
mssapi/utils.py
mssapi.egg-info/PKG-INFO
mssapi.egg-info/SOURCES.txt
mssapi.egg-info/dependency_links.txt
mssapi.egg-info/top_level.txt
mssapi/cacerts/__init__.py
mssapi/gs/__init__.py
mssapi/gs/acl.py
mssapi/gs/bucket.py
mssapi/gs/bucketlistresultset.py
mssapi/gs/connection.py
mssapi/gs/cors.py
mssapi/gs/key.py
mssapi/gs/lifecycle.py
mssapi/gs/resumable_upload_handler.py
mssapi/gs/user.py
mssapi/pyami/__init__.py
mssapi/pyami/bootstrap.py
mssapi/pyami/config.py
mssapi/pyami/copybot.py
mssapi/pyami/helloworld.py
mssapi/pyami/launch_ami.py
mssapi/pyami/scriptbase.py
mssapi/pyami/startup.py
mssapi/s3/__init__.py
mssapi/s3/acl.py
mssapi/s3/bucket.py
mssapi/s3/bucketlistresultset.py
mssapi/s3/bucketlogging.py
mssapi/s3/connection.py
mssapi/s3/deletemarker.py
mssapi/s3/key.py
mssapi/s3/keyfile.py
mssapi/s3/multidelete.py
mssapi/s3/multipart.py
mssapi/s3/prefix.py
mssapi/s3/resumable_download_handler.py
mssapi/s3/user.py
mssapi/s3/website.py
mssapi/vendored/__init__.py
mssapi/vendored/six.py
test/test_bucket.py
test/test_clean_bucket.py
test/test_connection.py
test/test_key.py
test/test_metadata.py
test/test_multipart.py
test/test_readme.py
test/test_util.py